AF_eraser/NMF.py
AF_eraser/__init__.py
AF_eraser/substraction.py
AF_eraser/utils.py
af_eraser-0.1.1.dist-info/licenses/LICENSE
af_eraser-0.1.1.dist-info/METADATA
af_eraser-0.1.1.dist-info/WHEEL
af_eraser-0.1.1.dist-info/top_level.txt
af_eraser-0.1.1.dist-info/RECORD
