Metadata-Version: 2.4
Name: AF_eraser
Version: 0.1.1
Summary: AF_eraser contains API tools to remove autofluorescent signal (background) from fluorescent microscopy images.
Author-email: Slimani Floric <floric.slimani@live.fr>
License-Expression: BSD-3-Clause
Project-URL: Homepage, https://github.com/SlimaniF/AF_eraser
Classifier: Programming Language :: Python :: 3
Classifier: Operating System :: OS Independent
Requires-Python: >=3.12
License-File: LICENSE
Requires-Dist: numpy
Requires-Dist: scipy
Dynamic: license-file
